docuverse/__init__.py
docuverse/docuverse_runner.py
docuverse/run_retrieval_modelrunner.py
docuverse/engines/__init__.py
docuverse/engines/data_template.py
docuverse/engines/retrieval_engine.py
docuverse/engines/search_corpus.py
docuverse/engines/search_data.py
docuverse/engines/search_engine.py
docuverse/engines/search_engine_config_params.py
docuverse/engines/search_queries.py
docuverse/engines/search_result.py
docuverse/engines/preprocessors/__init__.py
docuverse/engines/preprocessors/base_preprocessor.py
docuverse/engines/preprocessors/list_preprocessor.py
docuverse/engines/preprocessors/model_runner_preprocessor.py
docuverse/engines/reranking/__init__.py
docuverse/engines/reranking/dense_reranker.py
docuverse/engines/reranking/reranker.py
docuverse/engines/reranking/splade3_reranker.py
docuverse/engines/reranking/splade_reranker.py
docuverse/engines/retrieval/__init__.py
docuverse/engines/retrieval/retrieval_engine.py
docuverse/engines/retrieval/retrieval_servers.py
docuverse/engines/retrieval/search_filter.py
docuverse/engines/retrieval/elastic/__init__.py
docuverse/engines/retrieval/elastic/elastic.py
docuverse/engines/retrieval/elastic/elastic_bm25.py
docuverse/engines/retrieval/elastic/elastic_dense.py
docuverse/engines/retrieval/elastic/elastic_elser.py
docuverse/engines/retrieval/milvus/__init__.py
docuverse/engines/retrieval/milvus/milvus.py
docuverse/engines/retrieval/milvus/milvus_bm25.py
docuverse/engines/retrieval/milvus/milvus_dense.py
docuverse/engines/retrieval/milvus/milvus_hybrid.py
docuverse/engines/retrieval/milvus/milvus_sparse.py
docuverse/engines/retrieval/milvus/milvus_splade.py
docuverse/engines/retrieval/primeqa/__init__.py
docuverse/engines/retrieval/primeqa/primeqa.py
docuverse/engines/retrieval/primeqa/primeqa_colbert.py
docuverse/engines/retrieval/primeqa/primeqa_dpr.py
docuverse/engines/retrieval/vectordb/__init__.py
docuverse/engines/retrieval/vectordb/chromadb.py
docuverse/engines/retrieval/vectordb/faiss.py
docuverse-0.0.8.dist-info/LICENSE
docuverse-0.0.8.dist-info/METADATA
docuverse-0.0.8.dist-info/WHEEL
docuverse-0.0.8.dist-info/top_level.txt
docuverse-0.0.8.dist-info/RECORD
