Metadata-Version: 2.1
Name: docuverse
Version: 0.0.8
Summary: State-of-the-art Retrieval/Search engine models, including ElasticSearch, ChromaDB, Milvus, and PrimeQA
Home-page: https://github.com/primeqa/docuverse
Author: PrimeQA/DocUVerse Team
Author-email: primeqa@us.ibm.com
License: Apache
Keywords: Question Answering (QA),Machine Reading Comprehension (MRC),Information Retrieval (IR)
Classifier: Development Status :: 3 - Alpha
Classifier: Intended Audience :: Developers
Classifier: Intended Audience :: Science/Research
Classifier: Programming Language :: Python :: 3
Requires-Python: >=3.10.0, <3.12.0
License-File: LICENSE
Requires-Dist: rouge-score
Requires-Dist: pyyaml ~=6.0.1
Requires-Dist: sentence-transformers
Requires-Dist: python-dotenv ~=1.0.1
Requires-Dist: numpy ~=1.26.1
Requires-Dist: urllib3 ~=1.26.18
Requires-Dist: torch ~=2.3.1
Requires-Dist: tqdm ~=4.66.4
Requires-Dist: transformers ~=4.41.2
Requires-Dist: optimum[onnxruntime,openvino] ~=1.20.0
Requires-Dist: orjson ~=3.10.5
Requires-Dist: pydantic-core ~=2.24.0
Requires-Dist: simple-colors ~=0.1.5
Provides-Extra: all
Requires-Dist: rouge-score ; extra == 'all'
Requires-Dist: pyyaml ~=6.0.1 ; extra == 'all'
Requires-Dist: sentence-transformers ; extra == 'all'
Requires-Dist: python-dotenv ~=1.0.1 ; extra == 'all'
Requires-Dist: numpy ~=1.26.1 ; extra == 'all'
Requires-Dist: urllib3 ~=1.26.18 ; extra == 'all'
Requires-Dist: torch ~=2.3.1 ; extra == 'all'
Requires-Dist: tqdm ~=4.66.4 ; extra == 'all'
Requires-Dist: transformers ~=4.41.2 ; extra == 'all'
Requires-Dist: optimum[onnxruntime,openvino] ~=1.20.0 ; extra == 'all'
Requires-Dist: orjson ~=3.10.5 ; extra == 'all'
Requires-Dist: pydantic-core ~=2.24.0 ; extra == 'all'
Requires-Dist: simple-colors ~=0.1.5 ; extra == 'all'
Provides-Extra: install
Requires-Dist: rouge-score ; extra == 'install'
Requires-Dist: pyyaml ~=6.0.1 ; extra == 'install'
Requires-Dist: sentence-transformers ; extra == 'install'
Requires-Dist: python-dotenv ~=1.0.1 ; extra == 'install'
Requires-Dist: numpy ~=1.26.1 ; extra == 'install'
Requires-Dist: urllib3 ~=1.26.18 ; extra == 'install'
Requires-Dist: torch ~=2.3.1 ; extra == 'install'
Requires-Dist: tqdm ~=4.66.4 ; extra == 'install'
Requires-Dist: transformers ~=4.41.2 ; extra == 'install'
Requires-Dist: optimum[onnxruntime,openvino] ~=1.20.0 ; extra == 'install'
Requires-Dist: orjson ~=3.10.5 ; extra == 'install'
Requires-Dist: pydantic-core ~=2.24.0 ; extra == 'install'
Requires-Dist: simple-colors ~=0.1.5 ; extra == 'install'
